Metadata-Version: 1.1
Name: Y1z1nCalculator
Version: 0.0.3
Summary: Simple calc
Home-page: UNKNOWN
Author: Yazan Talib
Author-email: y1z1n.xx@gmail.com
License: MIT
Keywords: Y1z1nSimple
Platform: UNKNOWN
Classifier: Development Status :: 5 - Production/Stable
Classifier: Intended Audience :: Education
Classifier: Operating System :: Microsoft :: Windows :: Windows 10
Classifier: License :: OSI Approved :: MIT License
Classifier: Programming Language :: Python :: 3
